tracernaut/__init__.py
tracernaut/core.py
tracernaut-0.1.4.dist-info/licenses/LICENSE
tracernaut-0.1.4.dist-info/METADATA
tracernaut-0.1.4.dist-info/WHEEL
tracernaut-0.1.4.dist-info/top_level.txt
tracernaut-0.1.4.dist-info/RECORD
