Metadata-Version: 2.4
Name: tracernaut
Version: 0.1.4
Summary: Interactive code execution and memory visualization for Python in Jupyter
Author: Your Name
Author-email: Laio Oriel Seman <laio.seman@ufsc.br>
License: MIT License
Keywords: visualization,execution,tracing,debugging,jupyter,education
Classifier: Development Status :: 3 - Alpha
Classifier: Intended Audience :: Education
Classifier: Intended Audience :: Developers
Classifier: Programming Language :: Python :: 3
Classifier: Programming Language :: Python :: 3.7
Classifier: Programming Language :: Python :: 3.8
Classifier: Programming Language :: Python :: 3.9
Classifier: Programming Language :: Python :: 3.10
Classifier: Topic :: Education
Classifier: Topic :: Software Development :: Debuggers
Classifier: Framework :: Jupyter
Classifier: License :: OSI Approved :: MIT License
Classifier: Operating System :: OS Independent
Requires-Python: >=3.7
License-File: LICENSE
Requires-Dist: matplotlib
Requires-Dist: numpy
Requires-Dist: ipywidgets
Requires-Dist: adjustText
Dynamic: license-file
